{
  "main": {
    "name":"Mauro Dario Luna Ayala",
    "occupation":"Desarrollador Fullstack",
    "description":"Desarrollador Fullstack con experiencia en .NET. Buscandondo una posicion en la cual pueda seguir capacitandome en distintas tecnologias.",
    "image":"profilepic.jpg",
    "bio":"Use this bio section as your way of describing yourself and saying what you do, what technologies you like to use or feel most comfortable with, describing your personality, or whatever else you feel like throwing in.",
    "contactmessage":"Here is where you should write your message to readers to have them get in contact with you.",
    "email": "mauro.dario.luna.ayala@gmail.com",
    "phone": "11-36179601",
    "address":{
      "street":"",
      "city":"Berazategui",
      "state":"Buenos Aires",
      "zip": "",
      "country":"Argentina"
    },
    "website": "http://www.dev.com",
    "resumedownload":"http://dev.com",
    "social":[
      {
        "name":"linkedin",
        "url":"https://www.linkedin.com/in/tim-baker-8420009a/",
        "className":"fa fa-linkedin"
      },
      {
        "name":"github",
        "url":"http://github.com/tbakerx",
        "className":"fa fa-github"
      },
      {
        "name":"skype",
        "url":"http://skype.com",
        "className":"fa fa-skype"
      }
    ]
  },
  "resume":{
    "skillmessage":"Here you can create a short write-up of your skills to show off to employers",
    "education":[
      {
        "school":"Universidad de La Plata",
        "degree":"Licenciatura en informatica",
        "graduated":"",
        "description":"Describe your experience at school, what you learned, what useful skills you have acquired etc."
      },
      {
        "school":"School #1 Maybe College?",
        "degree":"What did you study 101",
        "graduated":"March 2003",
        "description":"Describe your experience at school, what you learned, what useful skills you have acquired etc."
      }
    ],
    "work":[
      {
        "company":"VR4 S.A",
        "title":"Desarrollador Fullstack ",
        "years":"Agost 2019 - Present",
        "description":"Desarrollo y mantenimiento de aplicaciones en .NET con front en Angular. Desarrollador RPA utilizando la herramienta UIPath."
      }
    ],
    "skills":[
      {
        "name":".NET",
        "level":"60%"
      },
      {
        "name":"Angular",
        "level":"55%"
      },
      {
        "name":"ReactJs",
        "level":"60 %"
      },
      {
        "name":"CSS",
        "level":"60%"
      },
      {
        "name":"HTML5",
        "level":"60%"
      },
      {
        "name":"VueJs",
        "level":"50%"
      },
      {
        "name":"SQLServer",
        "level":"80%"
      }
    ]
  },
  "portfolio":{
    "projects": [

 
    ]
  },
  "testimonials":{
    "testimonials":[
      {
        "text":"Lorem ipsum dolor sit amet, consectetur adipiscing elit. Vestibulum id felis non neque consequat tristique in non magna. Ut in pulvinar neque, sed viverra nisi. Fusce viverra odio sed cursus posuere. Quisque faucibus dictum arcu vitae tristique. Cras tempus, lacus sed venenatis accumsan, odio dui feugiat odio, in ultricies diam elit in enim. Cras et massa commodo, viverra elit vel, ultricies ipsum. Nullam vitae mattis lectus. Nulla et gravida magna. Proin quis dolor sed tellus elementum pharetra. Morbi lobortis efficitur purus. Vivamus consequat ut augue sed fringilla. Lorem ipsum dolor sit amet, consectetur adipiscing elit.",
        "user":"Mauro"
      }

    ]
  }
}
